lesezeichen/__init__.py
lesezeichen/cli.py
lesezeichen/lesezeichen.py
lesezeichen-0.0.4.dist-info/LICENSE
lesezeichen-0.0.4.dist-info/METADATA
lesezeichen-0.0.4.dist-info/WHEEL
lesezeichen-0.0.4.dist-info/entry_points.txt
lesezeichen-0.0.4.dist-info/top_level.txt
lesezeichen-0.0.4.dist-info/RECORD
